trading_platform/__init__.py
trading_platform/auth.py
trading_platform/cli.py
trading_platform/client.py
trading_platform/exceptions.py
trading_platform/market_data.py
trading_platform/orders.py
trading_platform/pnl.py
atwater_trading_platform-0.2.1.dist-info/METADATA
atwater_trading_platform-0.2.1.dist-info/WHEEL
atwater_trading_platform-0.2.1.dist-info/entry_points.txt
atwater_trading_platform-0.2.1.dist-info/top_level.txt
atwater_trading_platform-0.2.1.dist-info/RECORD
